{
	"auth": {
		"userPoolGroups": {
			"service": "Cognito-UserPool-Groups",
			"providerPlugin": "awscloudformation",
			"dependsOn": [
				{
					"category": "auth",
					"resourceName": "mediacloudproject",
					"attributes": [
						"UserPoolId",
						"AppClientIDWeb",
						"AppClientID",
						"IdentityPoolId"
					]
				}
			]
		},
		"mediacloudproject": {
			"service": "Cognito",
			"providerPlugin": "awscloudformation",
			"dependsOn": []
		}
	},
	"storage": {
		"s3a565a2da": {
			"service": "S3",
			"providerPlugin": "awscloudformation"
		}
	},
	"hosting": {
		"S3AndCloudFront": {
			"service": "S3AndCloudFront",
			"providerPlugin": "awscloudformation"
		}
	},
	"function": {},
	"api": {
		"mediacloudGraphQL": {
			"service": "AppSync",
			"providerPlugin": "awscloudformation",
			"output": {
				"authConfig": {
					"additionalAuthenticationProviders": [],
					"defaultAuthentication": {
						"authenticationType": "AMAZON_COGNITO_USER_POOLS",
						"userPoolConfig": {
							"userPoolId": "authmediacloudproject"
						}
					}
				}
			}
		}
	}
}